khal/__init__.py
khal/__main__.py
khal/_compat.py
khal/calendar_display.py
khal/cli.py
khal/cli_utils.py
khal/configwizard.py
khal/controllers.py
khal/custom_types.py
khal/exceptions.py
khal/icalendar.py
khal/parse_datetime.py
khal/plugins.py
khal/terminal.py
khal/utils.py
khal/version.py
khal/khalendar/__init__.py
khal/khalendar/backend.py
khal/khalendar/event.py
khal/khalendar/exceptions.py
khal/khalendar/khalendar.py
khal/khalendar/typing.py
khal/khalendar/vdir.py
khal/settings/__init__.py
khal/settings/exceptions.py
khal/settings/khal.spec
khal/settings/settings.py
khal/settings/utils.py
khal/ui/__init__.py
khal/ui/base.py
khal/ui/calendarwidget.py
khal/ui/colors.py
khal/ui/editor.py
khal/ui/widgets.py
khal-0.13.0.dist-info/licenses/doc/source/license.rst
khal-0.13.0.dist-info/METADATA
khal-0.13.0.dist-info/WHEEL
khal-0.13.0.dist-info/entry_points.txt
khal-0.13.0.dist-info/top_level.txt
khal-0.13.0.dist-info/RECORD
