Metadata-Version: 2.4
Name: khal
Version: 0.13.0
Summary: Standards based terminal calendar
Author-email: khal contributors <khal@lostpackets.de>
License-Expression: MIT
Project-URL: homepage, http://lostpackets.de/khal/
Project-URL: repository, https://github.com/pimutils/khal
Classifier: Development Status :: 4 - Beta
Classifier: Environment :: Console :: Curses
Classifier: Intended Audience :: End Users/Desktop
Classifier: Operating System :: POSIX
Classifier: Programming Language :: Python :: 3
Classifier: Programming Language :: Python :: 3 :: Only
Classifier: Programming Language :: Python :: 3.9
Classifier: Programming Language :: Python :: 3.10
Classifier: Programming Language :: Python :: 3.11
Classifier: Programming Language :: Python :: 3.12
Classifier: Programming Language :: Python :: 3.13
Classifier: Topic :: Communications
Classifier: Topic :: Utilities
Requires-Python: <3.14,>=3.9
License-File: doc/source/license.rst
Requires-Dist: click>=3.2
Requires-Dist: click_log>=0.2.0
Requires-Dist: icalendar>=6.0.0
Requires-Dist: urwid>=2.6.15
Requires-Dist: pyxdg
Requires-Dist: pytz
Requires-Dist: python-dateutil
Requires-Dist: configobj
Requires-Dist: tzlocal>=1.0
Provides-Extra: proctitle
Requires-Dist: setproctitle; extra == "proctitle"
Provides-Extra: test
Requires-Dist: pytest; extra == "test"
Requires-Dist: freezegun; extra == "test"
Requires-Dist: hypothesis; extra == "test"
Requires-Dist: packaging; extra == "test"
Requires-Dist: vdirsyncer; extra == "test"
Requires-Dist: setuptools; extra == "test"
Requires-Dist: importlib-metadata; python_version <= "3.9" and extra == "test"
Provides-Extra: docs
Requires-Dist: sphinx!=1.6.1; extra == "docs"
Requires-Dist: sphinxcontrib-newsfeed; extra == "docs"
Requires-Dist: sphinx-rtd-theme; extra == "docs"
Provides-Extra: all
Requires-Dist: khal[docs,proctitle,test]; extra == "all"
Dynamic: license-file
